aea_ledger_cosmos/__init__.py
aea_ledger_cosmos/cosmos.py
aea_ledger_cosmos/hashfuncs.py
aea_ledger_cosmos/py.typed
open_aea_ledger_cosmos-2.0.8.dist-info/licenses/LICENSE
open_aea_ledger_cosmos-2.0.8.dist-info/METADATA
open_aea_ledger_cosmos-2.0.8.dist-info/WHEEL
open_aea_ledger_cosmos-2.0.8.dist-info/entry_points.txt
open_aea_ledger_cosmos-2.0.8.dist-info/top_level.txt
open_aea_ledger_cosmos-2.0.8.dist-info/RECORD
