Metadata-Version: 2.4
Name: open-aea-ledger-cosmos
Version: 2.0.8
Summary: Python package wrapping the public and private key cryptography and ledger api of Cosmos.
Author: Valory AG
License: Apache-2.0
Classifier: Environment :: Console
Classifier: Environment :: Web Environment
Classifier: Development Status :: 5 - Production/Stable
Classifier: Intended Audience :: Developers
Classifier: License :: OSI Approved :: Apache Software License
Classifier: Natural Language :: English
Classifier: Operating System :: MacOS
Classifier: Operating System :: Microsoft
Classifier: Operating System :: Unix
Classifier: Programming Language :: Python :: 3.10
Classifier: Programming Language :: Python :: 3.11
Classifier: Topic :: Communications
Classifier: Topic :: Internet
Classifier: Topic :: Software Development
License-File: LICENSE
Requires-Dist: open-aea<3.0.0,>=2.0.0
Requires-Dist: ecdsa<0.17.0,>=0.15
Requires-Dist: bech32<2,>=1.2.0
Requires-Dist: pycryptodome<4.0.0,>=3.10.1
Requires-Dist: cosmpy==0.9.2
Dynamic: author
Dynamic: classifier
Dynamic: description
Dynamic: description-content-type
Dynamic: license
Dynamic: license-file
Dynamic: requires-dist
Dynamic: summary
